{
  "fill" : {
    "linear-gradient" : [
      "extended-srgb:0.20392,0.78039,0.34902,1.00000",
      "display-p3:0.68005,1.00000,0.69674,1.00000"
    ],
    "orientation" : {
      "start" : {
        "x" : 0.5,
        "y" : 0
      },
      "stop" : {
        "x" : 0.5,
        "y" : 0.7
      }
    }
  },
  "groups" : [
    {
      "blur-material" : null,
      "layers" : [
        {
          "image-name" : "Connecting The World.svg",
          "name" : "Connecting The World",
          "position" : {
            "scale" : 2.5,
            "translation-in-points" : [
              0.1994023379999703,
              141.42686158896078
            ]
          }
        }
      ],
      "position" : {
        "scale" : 2,
        "translation-in-points" : [
          0,
          0
        ]
      },
      "shadow" : {
        "kind" : "neutral",
        "opacity" : 0.5
      },
      "specular" : true,
      "translucency" : {
        "enabled" : true,
        "value" : 0.5
      }
    },
    {
      "blur-material" : null,
      "layers" : [
        {
          "image-name" : "nexaLogo.svg",
          "name" : "nexaLogo",
          "position" : {
            "scale" : 1.7,
            "translation-in-points" : [
              0,
              -87.27918525203704
            ]
          }
        }
      ],
      "lighting" : "combined",
      "shadow" : {
        "kind" : "neutral",
        "opacity" : 0.5
      },
      "specular" : true,
      "translucency" : {
        "enabled" : true,
        "value" : 0.5
      }
    }
  ],
  "supported-platforms" : {
    "circles" : [
      "watchOS"
    ],
    "squares" : "shared"
  }
}